superfocus_app/__init__.py
superfocus_app/do_alignment.py
superfocus_app/superfocus.py
superfocus_app/superfocus_downloadDB.py
superfocus_app/db/database_PKs.txt
superfocus_app/db/organisms2subsystem.txt
superfocus_app/db/focus_reduction/blast/.gitignore
superfocus_app/db/focus_reduction/diamond/.gitignore
superfocus_app/db/focus_reduction/rapsearch2/.gitignore
superfocus_app/db/static/blast/.gitignore
superfocus_app/db/static/diamond/.gitignore
superfocus_app/db/static/rapsearch2/.gitignore
superfocus_app/db/tmp/.gitignore
superfocus-1.4.1.dist-info/COPYING
superfocus-1.4.1.dist-info/METADATA
superfocus-1.4.1.dist-info/WHEEL
superfocus-1.4.1.dist-info/entry_points.txt
superfocus-1.4.1.dist-info/top_level.txt
superfocus-1.4.1.dist-info/RECORD
