Metadata-Version: 2.1
Name: superfocus
Version: 1.4.1
Summary: SUPER-FOCUS: A tool for agile functional analysis of shotgun metagenomic data
Home-page: https://github.com/metageni/super-focus
Author: Genivaldo G.Z. Silva
Author-email: genivaldo.gueiros@gmail.com
License: UNKNOWN
Keywords: superfocus_app
Platform: UNKNOWN
Classifier: Development Status :: 2 - Pre-Alpha
Classifier: Intended Audience :: Developers
Classifier: Natural Language :: English
Classifier: Programming Language :: Python :: 3.6
Classifier: Topic :: Scientific/Engineering :: Bio-Informatics
Requires-Dist: numpy (>=1.12.1)
Requires-Dist: scipy (>=0.19.0)
